metagit/__init__.py
metagit/_version.py
metagit/cli/__init__.py
metagit/cli/main.py
metagit/cli/commands/__init__.py
metagit/cli/commands/appconfig.py
metagit/cli/commands/config.py
metagit/cli/commands/detect.py
metagit/cli/commands/gitcache.py
metagit/cli/commands/init.py
metagit/cli/commands/project.py
metagit/cli/commands/project_repo.py
metagit/cli/commands/record.py
metagit/cli/commands/workspace.py
metagit/core/appconfig/__init__.py
metagit/core/appconfig/models.py
metagit/core/config/__init__.py
metagit/core/config/manager.py
metagit/core/config/models.py
metagit/core/detect/__init__.py
metagit/core/detect/manager.py
metagit/core/detect/models.py
metagit/core/detect/detectors/docker.py
metagit/core/detect/detectors/git.py
metagit/core/detect/detectors/python.py
metagit/core/detect/detectors/terraform.py
metagit/core/flows/detect_flow/__init__.py
metagit/core/flows/detect_flow/main.py
metagit/core/flows/detect_flow/crews/project_understanding_crew/project_understanding_crew.py
metagit/core/flows/detect_flow/crews/project_understanding_crew/config/agents.yaml
metagit/core/flows/detect_flow/crews/project_understanding_crew/config/tasks.yaml
metagit/core/flows/detect_flow/tools/__init__.py
metagit/core/flows/detect_flow/tools/human.py
metagit/core/flows/detect_flow/tools/index_tools.py
metagit/core/gitcache/README.md
metagit/core/gitcache/__init__.py
metagit/core/gitcache/config.py
metagit/core/gitcache/manager.py
metagit/core/project/manager.py
metagit/core/project/models.py
metagit/core/providers/__init__.py
metagit/core/providers/base.py
metagit/core/providers/github.py
metagit/core/providers/gitlab.py
metagit/core/record/__init__.py
metagit/core/record/manager.py
metagit/core/record/models.py
metagit/core/utils/click.py
metagit/core/utils/common.py
metagit/core/utils/files.py
metagit/core/utils/fuzzyfinder.py
metagit/core/utils/logging.py
metagit/core/utils/userprompt.py
metagit/core/utils/yaml_class.py
metagit/core/workspace/__init__.py
metagit_cli-0.1.10.dist-info/licenses/LICENSE
metagit_cli-0.1.10.dist-info/METADATA
metagit_cli-0.1.10.dist-info/WHEEL
metagit_cli-0.1.10.dist-info/entry_points.txt
metagit_cli-0.1.10.dist-info/top_level.txt
metagit_cli-0.1.10.dist-info/RECORD
