Metadata-Version: 2.4
Name: metagit-cli
Version: 0.1.10
Summary: Metagit-ai multi-repo management tool
Author-email: Zachary Loeber <zloeber@gmail.com>
Project-URL: Homepage, https://github.com/metagit-ai/metagit-cli
Project-URL: Documentation, https://metagit-ai.github.io/metagit-cli/
Project-URL: Issues, https://github.com/metagit-ai/metagit-cli/issues
Project-URL: CI, https://github.com/metagit-ai/metagit-cli/actions
Classifier: Programming Language :: Python :: 3
Classifier: Operating System :: OS Independent
Requires-Python: >=3.12
License-File: LICENSE
Requires-Dist: logging>=0.4.9.6
Requires-Dist: loguru>=0.7.3
Requires-Dist: pydantic>=2.11.4
Requires-Dist: requests>=2.32.3
Requires-Dist: click>=8.1.7
Requires-Dist: dotenv>=0.9.9
Requires-Dist: gitpython>=3.1.44
Requires-Dist: rich>=14.0.0
Requires-Dist: pyyaml>=6.0.2
Requires-Dist: pygithub>=2.6.1
Requires-Dist: jsonschema>=4.24.0
Requires-Dist: python-dotenv>=1.1.0
Requires-Dist: rapidfuzz>=3.13.0
Requires-Dist: tqdm>=4.66.4
Requires-Dist: types-tqdm>=4.67.0.20250516
Requires-Dist: aiofiles>=23.2.1
Requires-Dist: async>=0.6.2
Requires-Dist: setuptools-scm>=8.3.1
Requires-Dist: litellm>=1.74.8
Requires-Dist: crewai>=0.95.0
Requires-Dist: textual-dev>=1.7.0
Requires-Dist: tomli>=2.2.1
Requires-Dist: python-hcl2>=7.3.1
Provides-Extra: standard
Provides-Extra: test
Requires-Dist: pytest; extra == "test"
Requires-Dist: pytest-cov; extra == "test"
Requires-Dist: mypy; extra == "test"
Requires-Dist: ruff; extra == "test"
Requires-Dist: httpx; extra == "test"
Requires-Dist: pytest-asyncio; extra == "test"
Requires-Dist: black; extra == "test"
Provides-Extra: dev
Requires-Dist: ruff; extra == "dev"
Requires-Dist: black; extra == "dev"
Requires-Dist: isort; extra == "dev"
Requires-Dist: mypy; extra == "dev"
Provides-Extra: docs
Requires-Dist: mkdocs; extra == "docs"
Requires-Dist: mkdocs-material; extra == "docs"
Requires-Dist: mkdocstrings; extra == "docs"
Requires-Dist: mkdocs-click; extra == "docs"
Requires-Dist: mdtoc; extra == "docs"
Requires-Dist: mkdocs-mermaid2-plugin; extra == "docs"
Requires-Dist: mkdocs-material; extra == "docs"
Provides-Extra: lint
Requires-Dist: ruff; extra == "lint"
Requires-Dist: black; extra == "lint"
Requires-Dist: isort; extra == "lint"
Requires-Dist: mypy; extra == "lint"
Provides-Extra: format
Requires-Dist: black; extra == "format"
Requires-Dist: isort; extra == "format"
Provides-Extra: typecheck
Requires-Dist: mypy; extra == "typecheck"
Dynamic: license-file
